{
  "version": "0.2",
  "language": "en",
  "useGitignore": true,
  "files": [
    ".github/workflows/**/*.yml",
    "data/posts/2025-08-15-welcome-to-dout-dev-2.md",
    "data/posts/2026-04-04-how-i-built-dout-dev.md",
    "scripts/build-assets.js",
    "scripts/check-favicons.js",
    "scripts/verify-dist.cjs",
    "scripts/cms/**/*.js",
    "scripts/linting/**/*.js",
    "src/components/**/*.html",
    "src/layouts/**/*.html",
    "src/scripts/analytics.js",
    "src/scripts/main.js",
    "src/scripts/search.js",
    "src/templates/**/*.html"
  ],
  "ignorePaths": [
    "**/*.test.js",
    "dist/**",
    "docs/**",
    "node_modules/**",
    "playwright-report/**",
    "scripts/cms/tests/**",
    "scripts/template-engine/tests/**",
    "src/data/**",
    "src/months/**",
    "src/posts/**",
    "src/series/**",
    "src/tags/**",
    "test-results/**",
    "tests/visual/**"
  ],
  "ignoreRegExpList": ["/https?:\\/\\/[^\\s)]+/g", "/[A-Za-z0-9_-]+\\.(png|jpg|jpeg|svg|webp|xml|json|html|css|js)/g"],
  "words": [
    "àèéìòóù",
    "ÀÈÉÌÒÓÙ",
    "Avenir",
    "apos",
    "CodePen",
    "Cascadia",
    "Consolas",
    "Candara",
    "Bitstream",
    "Emiliano",
    "Giscus",
    "Menlo",
    "Neue",
    "Palatino",
    "Pisu",
    "Srcsets",
    "Segoe",
    "WCAG",
    "a11y",
    "antiqua",
    "dout",
    "favicons",
    "fetchpriority",
    "flexbox",
    "formaction",
    "graymatter",
    "haspopup",
    "highlighter",
    "focusables",
    "hrefs",
    "infostring",
    "inclusivity",
    "labelledby",
    "lede",
    "mozjpeg",
    "nojekyll",
    "noteref",
    "noopener",
    "noreferrer",
    "pixu",
    "popovertarget",
    "popovertargetaction",
    "prerendered",
    "referrerpolicy",
    "scrollspy",
    "serie",
    "striptags",
    "stopwords",
    "srcset",
    "TTFB",
    "urlencode",
    "viewbox",
    "webp",
    "xlink"
  ]
}
